AUTHORS.rst
CONTRIBUTING.rst
HISTORY.rst
LICENSE
MANIFEST.in
README.rst
setup.cfg
setup.py
docs/Makefile
docs/authors.rst
docs/conf.py
docs/contributing.rst
docs/history.rst
docs/index.rst
docs/installation.rst
docs/make.bat
docs/readme.rst
docs/usage.rst
docs/_build/html/_static/ajax-loader.gif
docs/_build/html/_static/comment-bright.png
docs/_build/html/_static/comment-close.png
docs/_build/html/_static/comment.png
docs/_build/html/_static/down-pressed.png
docs/_build/html/_static/down.png
docs/_build/html/_static/file.png
docs/_build/html/_static/minus.png
docs/_build/html/_static/plus.png
docs/_build/html/_static/up-pressed.png
docs/_build/html/_static/up.png
msnc/__init__.py
msnc/dataset.py
msnc/encoder.py
msnc/model.py
msnc/util.py
msnc.egg-info/PKG-INFO
msnc.egg-info/SOURCES.txt
msnc.egg-info/dependency_links.txt
msnc.egg-info/not-zip-safe
msnc.egg-info/requires.txt
msnc.egg-info/top_level.txt
tests/__init__.py
tests/test_average_encoder.py
tests/test_model.py
tests/test_recurrent_encoder.py